dpipes/__init__.py
dpipes/pipeline.py
dpipes/processor.py
dpipes-0.1.1.dist-info/METADATA
dpipes-0.1.1.dist-info/WHEEL
dpipes-0.1.1.dist-info/top_level.txt
dpipes-0.1.1.dist-info/RECORD
