Metadata-Version: 2.1
Name: dpipes
Version: 0.1.1
Summary: dPipes - Pythonic Data Pipelines
Author-email: Chris Santiago <cjsantiago@gatech.edu>
License: MIT
Project-URL: Sourcecode, https://github.com/chris-santiago/dpipes
Project-URL: Documentation, https://chris-santiago.github.io/dpipes/
Requires-Python: >=3.8
Requires-Dist: pandas (>=1.0.0)
Provides-Extra: demo
Requires-Dist: polars (>=0.17.9) ; extra == 'demo'
Requires-Dist: openpyxl (>=3.1.2) ; extra == 'demo'
Requires-Dist: nltk (>=3.8.1) ; extra == 'demo'
